.gitignore
CHANGES.txt
CONTRIBUTORS.txt
COPYRIGHT.txt
LICENSE.txt
README.txt
TODO.txt
setup.cfg
setup.py
tox.ini
docs/Makefile
docs/changes.rst
docs/conf.py
docs/index.rst
docs/narr.rst
docs/.static/logo_hi.gif
docs/.static/repoze.css
repoze/__init__.py
repoze.zodbconn.egg-info/PKG-INFO
repoze.zodbconn.egg-info/SOURCES.txt
repoze.zodbconn.egg-info/dependency_links.txt
repoze.zodbconn.egg-info/entry_points.txt
repoze.zodbconn.egg-info/namespace_packages.txt
repoze.zodbconn.egg-info/not-zip-safe
repoze.zodbconn.egg-info/requires.txt
repoze.zodbconn.egg-info/top_level.txt
repoze/zodbconn/__init__.py
repoze/zodbconn/_compat.py
repoze/zodbconn/cachecleanup.py
repoze/zodbconn/connector.py
repoze/zodbconn/datatypes.py
repoze/zodbconn/finder.py
repoze/zodbconn/middleware.py
repoze/zodbconn/resolvers.py
repoze/zodbconn/transferlog.py
repoze/zodbconn/uri.py
repoze/zodbconn/tests/__init__.py
repoze/zodbconn/tests/test_cachecleanup.py
repoze/zodbconn/tests/test_connector.py
repoze/zodbconn/tests/test_finder.py
repoze/zodbconn/tests/test_middleware.py
repoze/zodbconn/tests/test_resolvers.py
repoze/zodbconn/tests/test_transferlog.py
repoze/zodbconn/tests/test_uri.py